PySingular.cpython-311-x86_64-linux-gnu.so
passagemath_singular/__init__.py
passagemath_singular.libs/libSingular-4-17362f35.4.1.so
passagemath_singular.libs/libcddgmp-21acf0c6.so.0.1.3
passagemath_singular.libs/libfactory-4-023c8793.4.1.so
passagemath_singular.libs/libflint-ea9ec694.so.22.0.0
passagemath_singular.libs/libgf2x-a4cdec90.so.3.0.0
passagemath_singular.libs/libgfortran-83c28eba.so.5.0.0
passagemath_singular.libs/libgmp-6e109695.so.10.5.0
passagemath_singular.libs/libgsl-cda90e79.so.28.0.0
passagemath_singular.libs/libmpfr-104d25bb.so.6.2.2
passagemath_singular.libs/libntl-bacfd860.so.45.0.0
passagemath_singular.libs/libomalloc-0-5c9e866e.9.6.so
passagemath_singular.libs/libopenblasp-r0-6dcb67f9.3.29.so
passagemath_singular.libs/libpolys-4-5b4f3f86.4.1.so
passagemath_singular.libs/libquadmath-2284e583.so.0.0.0
passagemath_singular.libs/libreadline-ea270e21.so.8.2
passagemath_singular.libs/libsingular_resources-4-a1aafc6d.4.1.so
passagemath_singular.libs/libtinfo-ceb117d9.so.6.3
sage/all__sagemath_singular.py
sage/algebras/all__sagemath_singular.py
sage/algebras/fusion_rings/all.py
sage/algebras/fusion_rings/f_matrix.py
sage/algebras/fusion_rings/fast_parallel_fmats_methods.cpython-311-x86_64-linux-gnu.so
sage/algebras/fusion_rings/fast_parallel_fmats_methods.pxd
sage/algebras/fusion_rings/fast_parallel_fmats_methods.pyx
sage/algebras/fusion_rings/fast_parallel_fusion_ring_braid_repn.cpython-311-x86_64-linux-gnu.so
sage/algebras/fusion_rings/fast_parallel_fusion_ring_braid_repn.pxd
sage/algebras/fusion_rings/fast_parallel_fusion_ring_braid_repn.pyx
sage/algebras/fusion_rings/fusion_double.py
sage/algebras/fusion_rings/fusion_ring.py
sage/algebras/fusion_rings/poly_tup_engine.cpython-311-x86_64-linux-gnu.so
sage/algebras/fusion_rings/poly_tup_engine.pxd
sage/algebras/fusion_rings/poly_tup_engine.pyx
sage/algebras/fusion_rings/shm_managers.cpython-311-x86_64-linux-gnu.so
sage/algebras/fusion_rings/shm_managers.pxd
passagemath_singular-10.6.43.dist-info/METADATA
passagemath_singular-10.6.43.dist-info/WHEEL
passagemath_singular-10.6.43.dist-info/top_level.txt
passagemath_singular-10.6.43.dist-info/RECORD
passagemath_singular-10.6.43.dist-info/sboms/auditwheel.cdx.json
