Metadata-Version: 2.4
Name: passagemath-singular
Version: 10.6.43
Summary: passagemath: Computer algebra, algebraic geometry, singularity theory with Singular
Author-email: The Sage Developers <sage-support@googlegroups.com>
Maintainer: Matthias Köppe, passagemath contributors
License-Expression: GPL-2.0-or-later
Project-URL: release notes, https://github.com/passagemath/passagemath/releases
Project-URL: repo (upstream), https://github.com/sagemath/sage
Project-URL: repo, https://github.com/passagemath/passagemath
Project-URL: documentation, https://passagemath.org/docs/latest
Project-URL: homepage (upstream), https://www.sagemath.org
Project-URL: discourse, https://passagemath.discourse.group
Project-URL: tracker (upstream), https://github.com/sagemath/sage/issues
Project-URL: tracker, https://github.com/passagemath/passagemath/issues
Classifier: Development Status :: 6 - Mature
Classifier: Intended Audience :: Education
Classifier: Intended Audience :: Science/Research
Classifier: Operating System :: POSIX
Classifier: Operating System :: POSIX :: Linux
Classifier: Operating System :: MacOS :: MacOS X
Classifier: Programming Language :: Python :: 3 :: Only
Classifier: Programming Language :: Python :: 3.10
Classifier: Programming Language :: Python :: 3.11
Classifier: Programming Language :: Python :: 3.12
Classifier: Programming Language :: Python :: 3.13
Classifier: Programming Language :: Python :: 3.14
Classifier: Programming Language :: Python :: Implementation :: CPython
Classifier: Topic :: Scientific/Engineering :: Mathematics
Requires-Python: <3.15,>=3.10
Requires-Dist: passagemath-pari~=10.6.43.0
Requires-Dist: cysignals!=1.12.4; sys_platform == "win32"
Requires-Dist: cysignals!=1.12.0,>=1.11.2
Requires-Dist: memory_allocator
Requires-Dist: pexpect>=4.8.0
Requires-Dist: passagemath-environment~=10.6.43.0
Requires-Dist: passagemath-categories~=10.6.43.0
Requires-Dist: passagemath-modules~=10.6.43.0
Requires-Dist: passagemath-flint~=10.6.43.0
Provides-Extra: test
Requires-Dist: passagemath-repl; extra == "test"
Provides-Extra: jupyterkernel
Requires-Dist: passagemath-singular-jupyterkernel; extra == "jupyterkernel"
Provides-Extra: jupyterlab
Requires-Dist: passagemath-singular[jupyterkernel]; extra == "jupyterlab"
Requires-Dist: jupyterlab; extra == "jupyterlab"
Provides-Extra: notebook
Requires-Dist: passagemath-singular[jupyterkernel]; extra == "notebook"
Requires-Dist: notebook>=6.1.1; extra == "notebook"
